Njalla/API.py
Njalla/Domain.py
Njalla/Server.py
Njalla/VPN.py
Njalla/Wallet.py
Njalla/__init__.py
njalla-0.9.0.dist-info/licenses/LICENSE
tests/__init__.py
tests/test_api.py
tests/test_domain.py
tests/test_server.py
tests/test_vpn.py
tests/test_wallet.py
njalla-0.9.0.dist-info/METADATA
njalla-0.9.0.dist-info/WHEEL
njalla-0.9.0.dist-info/top_level.txt
njalla-0.9.0.dist-info/RECORD
