Metadata-Version: 2.4
Name: Njalla
Version: 0.9.0
Summary: A python library built to integrate the njal.la API
Home-page: https://github.com/DevCa-IO/Njalla/
Author: Luca from DevCa
Author-email: luca@devca.io
Project-URL: Bug Tracker, https://github.com/DevCa-IO/Njalla/issues
Project-URL: Documentation, https://github.com/DevCa-IO/Njalla/
Project-URL: Source Code, https://github.com/DevCa-IO/Njalla/
Project-URL: Release Notes, https://github.com/DevCa-IO/Njalla/releases
Classifier: Programming Language :: Python :: 3.7
Classifier: Programming Language :: Python :: 3.8
Classifier: Programming Language :: Python :: 3.9
Classifier: Programming Language :: Python :: 3.10
Classifier: Programming Language :: Python :: 3.11
Classifier: Programming Language :: Python :: 3.12
Classifier: License :: OSI Approved :: MIT License
Classifier: Operating System :: OS Independent
Classifier: Topic :: Software Development :: Libraries :: Python Modules
Classifier: Topic :: Internet :: WWW/HTTP
Classifier: Topic :: Utilities
License-File: LICENSE
Requires-Dist: requests
Dynamic: license-file
Dynamic: requires-dist
